[
  {
    "year": "2018",
    "lei": "FRONTENDTESTBANK9999",
    "name": "Frontend Test Bank",
    "taxId": "53-1111111",
    "quarterlyFiler": false
  },
  {
    "year": "2019",
    "lei": "FRONTENDTESTBANK9999",
    "name": "Frontend Test Bank",
    "taxId": "53-1111111",
    "quarterlyFiler": false
  },
  {
    "year": "2020",
    "lei": "FRONTENDTESTBANK9999",
    "name": "Frontend Test Bank",
    "taxId": "53-1111111",
    "quarterlyFiler": true
  },
  {
    "year": "2018",
    "lei": "B90YWS6AFX2LGWOXJ1LD",
    "name": "Platform Test Bank 0",
    "taxId": "01-0123456",
    "quarterlyFiler": false
  },
  {
    "year": "2019",
    "lei": "B90YWS6AFX2LGWOXJ1LD",
    "name": "Platform Test Bank 0",
    "taxId": "01-0123456",
    "quarterlyFiler": false
  },
  {
    "year": "2020",
    "lei": "B90YWS6AFX2LGWOXJ1LD",
    "name": "Platform Test Bank 0",
    "taxId": "01-0123456",
    "quarterlyFiler": true
  }]
